CHANGES.txt
CONTRIBUTORS.txt
MANIFEST.in
README.txt
bootstrap.py
buildout.cfg
setup.cfg
setup.py
docs/LICENSE.txt
docs/agpl-3.0.txt
src/wasgehtengine/__init__.py
src/wasgehtengine.policy.egg-info/PKG-INFO
src/wasgehtengine.policy.egg-info/SOURCES.txt
src/wasgehtengine.policy.egg-info/dependency_links.txt
src/wasgehtengine.policy.egg-info/entry_points.txt
src/wasgehtengine.policy.egg-info/namespace_packages.txt
src/wasgehtengine.policy.egg-info/not-zip-safe
src/wasgehtengine.policy.egg-info/requires.txt
src/wasgehtengine.policy.egg-info/top_level.txt
src/wasgehtengine/policy/__init__.py
src/wasgehtengine/policy/configure.zcml
src/wasgehtengine/policy/setuphandlers.py
src/wasgehtengine/policy/testing.py
src/wasgehtengine/policy/profiles/default/metadata.xml
src/wasgehtengine/policy/profiles/default/properties.xml
src/wasgehtengine/policy/profiles/default/wasgehtengine.policy-various.txt
src/wasgehtengine/policy/profiles/default/structure/.objects
src/wasgehtengine/policy/profiles/default/structure/.preserve
src/wasgehtengine/policy/profiles/default/structure/blog/.properties
src/wasgehtengine/policy/profiles/default/structure/eventimportstatus/.properties
src/wasgehtengine/policy/profiles/default/structure/events/.properties
src/wasgehtengine/policy/profiles/default/structure/osmimportstatus/.properties
src/wasgehtengine/policy/profiles/default/structure/screenings/.properties
src/wasgehtengine/policy/profiles/default/structure/venues/.properties
src/wasgehtengine/policy/profiles/testing/metadata.xml
src/wasgehtengine/policy/tests/__init__.py
src/wasgehtengine/policy/tests/test_example.py