Metadata-Version: 1.1
Name: wasgehtengine.policy
Version: 1.4.0
Summary: Wasgehtengine Site Policy
Home-page: https://gitorious.org/wasgehtengine
Author: Fabian Köster
Author-email: koesterreich@fastmail.fm
License: agpl
Platform: UNKNOWN
Classifier: Environment :: Web Environment
Classifier: Framework :: Plone
Classifier: Operating System :: OS Independent
Classifier: Programming Language :: Python
Classifier: Programming Language :: Python :: 2.7
Classifier: Topic :: Software Development :: Libraries :: Python Modules
